[{"movie_genre":"Action|Drama","movie_title":"Zatoichi Challenged (Zatôichi chikemuri kaidô) (Zatôichi 17)"},
{"movie_genre":"Comedy","movie_title":"Lammbock"},
{"movie_genre":"Drama|Thriller","movie_title":"Forbidden"},
{"movie_genre":"Comedy|Drama","movie_title":"Kotch"},
{"movie_genre":"Action|Adventure|Comedy","movie_title":"Kung Fu Dunk"},
{"movie_genre":"Comedy|Drama","movie_title":"Happy, Happy (Sykt lykkelig)"},
{"movie_genre":"Drama","movie_title":"The Green"},
{"movie_genre":"Documentary","movie_title":"Hijacking Catastrophe: 9/11, Fear & the Selling of American Empire"},
{"movie_genre":"Drama|Sci-Fi|Thriller","movie_title":"The Butterfly Effect"},
{"movie_genre":"Adventure|Fantasy","movie_title":"Magic Voyage of Sindbad, The (Sadko)"},
{"movie_genre":"Comedy|Drama|Romance","movie_title":"Peter and Vandy"},
{"movie_genre":"Adventure|Comedy|Crime|Romance","movie_title":"Brothers Bloom, The"},
{"movie_genre":"Drama|Romance","movie_title":"Promise, The (Versprechen, Das)"},
{"movie_genre":"Action|Comedy|Documentary","movie_title":"Nitro Circus: The Movie"},
{"movie_genre":"Comedy|Crime","movie_title":"Triggermen"},
{"movie_genre":"Drama","movie_title":"My Brother's Wife (Mujer de mi hermano, La)"},
{"movie_genre":"Action|Adventure|Drama|War","movie_title":"Legionnaire"},
{"movie_genre":"Action|Horror|Sci-Fi|Thriller","movie_title":"Alien³ (a.k.a. Alien 3)"},
{"movie_genre":"Drama|War","movie_title":"One Man's Hero"},
{"movie_genre":"Drama","movie_title":"State of Things, The (Stand der Dinge, Der)"},
{"movie_genre":"Comedy|Crime","movie_title":"Very Bad Things"},
{"movie_genre":"Drama|Romance|War","movie_title":"White Cliffs of Dover, The"},
{"movie_genre":"Comedy","movie_title":"Gigi"},
{"movie_genre":"Crime|Drama|Horror|Thriller","movie_title":"Shuttle"},
{"movie_genre":"Comedy","movie_title":"Bizarre, Bizarre (Drôle de drame ou L'étrange aventure de Docteur Molyneux)"},
{"movie_genre":"Drama|Fantasy|Horror|Mystery","movie_title":"Face to Face (Ansikte mot ansikte)"},
{"movie_genre":"Animation|Comedy","movie_title":"Isabelle au bois dormant"},
{"movie_genre":"Comedy","movie_title":"Serial"},
{"movie_genre":"Drama","movie_title":"3 Backyards"},
{"movie_genre":"Comedy|Drama","movie_title":"We Bought a Zoo"},
{"movie_genre":"Comedy","movie_title":"Morgan Stewart's Coming Home"},
{"movie_genre":"Comedy","movie_title":"Sex Tape"},
{"movie_genre":"Comedy|Fantasy","movie_title":"Ted"},
{"movie_genre":"Drama|Thriller","movie_title":"Canyons, The"},
{"movie_genre":"Crime|Thriller","movie_title":"Albino Alligator"},
{"movie_genre":"Comedy","movie_title":"Little Bit of Soul, A"},
{"movie_genre":"Drama","movie_title":"Othello"},
{"movie_genre":"Comedy|Drama","movie_title":"Mrs. Henderson Presents"},
{"movie_genre":"Action|Adventure","movie_title":"Tarzan and His Mate"},
{"movie_genre":"Drama","movie_title":"Shoeshine (Sciuscià)"},
{"movie_genre":"Comedy","movie_title":"De Dana Dan"},
{"movie_genre":"Comedy|Drama","movie_title":"Holy Flying Circus"},
{"movie_genre":"Horror|Thriller","movie_title":"Red State"},
{"movie_genre":"Documentary","movie_title":"Stevie"},
{"movie_genre":"Action|Drama|Thriller","movie_title":"Business of Strangers, The"},
{"movie_genre":"Comedy","movie_title":"Living with the Fosters"},
{"movie_genre":"Drama","movie_title":"Cold Water (Eau Froide, L')"},
{"movie_genre":"Action|Adventure|Drama","movie_title":"Milarepa"},
{"movie_genre":"Comedy|Drama|Mystery|Romance","movie_title":"Daytrippers, The"},
{"movie_genre":"Drama","movie_title":"Cherry Orchard, The (Sakura no sono)"},
{"movie_genre":"Drama","movie_title":"Seduction of Joe Tynan, The"},
{"movie_genre":"Children|Drama","movie_title":"Black Beauty"},
{"movie_genre":"Drama","movie_title":"Nothing's All Bad"},
{"movie_genre":"Drama|Western","movie_title":"Salvation, The"},
{"movie_genre":"Comedy","movie_title":"Happy Time, The"},
{"movie_genre":"Horror|Sci-Fi","movie_title":"Terror is a Man"},
{"movie_genre":"Drama","movie_title":"Limbo"},
{"movie_genre":"Drama|Horror|Thriller","movie_title":"Godspeed"},
{"movie_genre":"Drama","movie_title":"Six Weeks"},
{"movie_genre":"Crime|Drama","movie_title":"I'll Sleep When I'm Dead"},
{"movie_genre":"Comedy","movie_title":"Do Not Disturb"},
{"movie_genre":"Horror|Sci-Fi","movie_title":"Invisible Ray, The"},
{"movie_genre":"Comedy|Horror","movie_title":"Ghost Breakers, The"},
{"movie_genre":"Drama|War","movie_title":"Unknown Soldier, The (Tuntematon sotilas)"},
{"movie_genre":"Drama|Thriller","movie_title":"Rollercoaster"},
{"movie_genre":"Comedy|Crime","movie_title":"King's Ransom"},
{"movie_genre":"Drama|Romance","movie_title":"Our Daily Bread"},
{"movie_genre":"Action|Thriller","movie_title":"Streets of Blood"},
{"movie_genre":"Documentary","movie_title":"Mondo Topless"},
{"movie_genre":"Action|Drama|Sci-Fi","movie_title":"Meteor"},
{"movie_genre":"Drama","movie_title":"Song of the Bloodred Flower (Laulu tulipunaisesta kukasta)"},
{"movie_genre":"Crime","movie_title":"Coup de torchon (Clean Slate)"},
{"movie_genre":"Action|Sci-Fi|Thriller","movie_title":"Virtuosity"},
{"movie_genre":"Drama","movie_title":"Princess (Prinsessa)"},
{"movie_genre":"Comedy|Drama","movie_title":"Rare Birds"},
{"movie_genre":"Adventure|Fantasy","movie_title":"Jack the Giant Killer"},
{"movie_genre":"Drama|Mystery|Romance","movie_title":"Northern Lights"},
{"movie_genre":"Drama|War","movie_title":"Occurrence at Owl Creek Bridge, An (La rivière du hibou)"},
{"movie_genre":"Comedy|Drama","movie_title":"Big Picture, The"},
{"movie_genre":"Drama|Horror|Thriller","movie_title":"Misery"},
{"movie_genre":"Crime|Drama","movie_title":"Jericho Mile, The"},
{"movie_genre":"Crime|Drama|Film-Noir","movie_title":"Glass Web, The"},
{"movie_genre":"Comedy|Romance","movie_title":"Head Over Heels"},
{"movie_genre":"Drama|Romance","movie_title":"Smooth Talk"},
{"movie_genre":"Drama","movie_title":"Chosen, The"},
{"movie_genre":"Adventure","movie_title":"Dinosaur Project, The"},
{"movie_genre":"Comedy|Drama","movie_title":"Grandpa for Christmas, A (Bert & Becca)"},
{"movie_genre":"Drama","movie_title":"Forbidden Christ, The (Cristo proibito, Il)"},
{"movie_genre":"Drama","movie_title":"City of Hope"},
{"movie_genre":"Drama","movie_title":"Civil Action, A"},
{"movie_genre":"Drama","movie_title":"Every Night Dreams (Each Night I Dream) (Yogoto no yume)"},
{"movie_genre":"Comedy","movie_title":"Fun with Dick and Jane"},
{"movie_genre":"Action|Adventure","movie_title":"Hercules"},
{"movie_genre":"Drama","movie_title":"Mahoney's Last Stand"},
{"movie_genre":"Drama","movie_title":"Saint of Fort Washington, The"},
{"movie_genre":"Horror|Thriller","movie_title":"Hellgate"},
{"movie_genre":"Action|Mystery","movie_title":"Duelist (Hyeongsa)"},
{"movie_genre":"Crime|Drama|Film-Noir","movie_title":"House by the River"},
{"movie_genre":"Sci-Fi","movie_title":"Angry Red Planet, The"},
{"movie_genre":"Adventure|Animation|Fantasy|IMAX","movie_title":"Rise of the Guardians"},
{"movie_genre":"Comedy|Drama","movie_title":"Curly Sue"},
{"movie_genre":"Crime|Drama","movie_title":"The Stoker"},
{"movie_genre":"Action|Adventure|Crime","movie_title":"K-20: The Fiend with Twenty Faces"},
{"movie_genre":"Drama|Film-Noir","movie_title":"Born to Be Bad"},
{"movie_genre":"Crime|Thriller","movie_title":"Century of the Dragon (Long zai bian yuan)"},
{"movie_genre":"Comedy|Crime|Romance","movie_title":"Hit by Lightning"},
{"movie_genre":"Drama|Romance","movie_title":"Feast of Love"},
{"movie_genre":"Comedy","movie_title":"Once Upon a Scoundrel"},
{"movie_genre":"Comedy","movie_title":"La Première étoile"},
{"movie_genre":"Drama","movie_title":"Molly Maguires, The"},
{"movie_genre":"Drama","movie_title":"Batch '81"},
{"movie_genre":"Comedy|Drama","movie_title":"Follow Me, Boys!"},
{"movie_genre":"Comedy|Drama","movie_title":"Vizontele Tuuba"},
{"movie_genre":"Animation|Children","movie_title":"Charlotte's Web"},
{"movie_genre":"Drama","movie_title":"For Ever Mozart"},
{"movie_genre":"Horror","movie_title":"Devil Rides Out, The"},
{"movie_genre":"Drama","movie_title":"Dark at the Top of the Stairs, The"},
{"movie_genre":"Drama","movie_title":"Eve's Bayou"},
{"movie_genre":"Comedy","movie_title":"Jay Mohr: Funny for a Girl"},
{"movie_genre":"Crime|Fantasy|Horror","movie_title":"Cabinet of Dr. Caligari, The (Cabinet des Dr. Caligari., Das)"},
{"movie_genre":"Crime|Drama|Romance|Thriller","movie_title":"Next Three Days, The"},
{"movie_genre":"Crime|Drama|Thriller|Western","movie_title":"Killer Inside Me, The"},
{"movie_genre":"Action","movie_title":"Taxi Hunter (Di shi pan guan)"},
{"movie_genre":"Action|Thriller","movie_title":"3000 Miles to Graceland"},
{"movie_genre":"Action|Comedy|Horror","movie_title":"Citizen Toxie: The Toxic Avenger IV"},
{"movie_genre":"Horror|Thriller","movie_title":"Locals, The"},
{"movie_genre":"Action|Comedy","movie_title":"Wrongfully Accused"},
{"movie_genre":"Drama","movie_title":"Strip-tease"},
{"movie_genre":"Action","movie_title":"Never Back Down"},
{"movie_genre":"Action|Crime|Drama|Mystery|Sci-Fi|Thriller","movie_title":"Strange Days"},
{"movie_genre":"Crime|Drama|Thriller","movie_title":"Bring Me the Head of Alfredo Garcia"},
{"movie_genre":"Action|Adventure|Fantasy|Sci-Fi","movie_title":"Hercules and the Lost Kingdom"},
{"movie_genre":"Animation|Fantasy|Horror|Sci-Fi","movie_title":"Wicked City (Yôjû toshi)"},
{"movie_genre":"Adventure|Comedy|Musical","movie_title":"Tenacious D in The Pick of Destiny"},
{"movie_genre":"Drama|Fantasy|Thriller","movie_title":"Curse of the Oily Man (Sumpah orang minyak) "},
{"movie_genre":"Drama|Thriller","movie_title":"After Last Season"},
{"movie_genre":"Drama|Romance","movie_title":"Love Don't Cost a Thing"},
{"movie_genre":"Action|Comedy","movie_title":"Nude Nuns with Big Guns"},
{"movie_genre":"Drama","movie_title":"My Bodyguard"},
{"movie_genre":"Comedy|Drama|Fantasy","movie_title":"Wrestler, The (Painija)"},
{"movie_genre":"Drama|Musical","movie_title":"Nob Hill"},
{"movie_genre":"Comedy","movie_title":"Hollywood Knights, The"},
{"movie_genre":"Crime|Drama|Film-Noir|Thriller","movie_title":"Street with No Name, The"},
{"movie_genre":"Comedy|Crime|Drama|War","movie_title":"Wounds, The (Rane)"},
{"movie_genre":"Horror","movie_title":"Grotesque"},
{"movie_genre":"Comedy|Drama|Romance","movie_title":"Mad Dog and Glory"},
{"movie_genre":"Children|Comedy","movie_title":"House Arrest"},
{"movie_genre":"Drama|Romance","movie_title":"Painted Veil, The"},
{"movie_genre":"Drama","movie_title":"Viola"},
{"movie_genre":"Comedy|Fantasy|Mystery|Sci-Fi","movie_title":"Nothing"},
{"movie_genre":"Action|Crime|Mystery|Romance|Thriller","movie_title":"Don 2"},
{"movie_genre":"Drama","movie_title":"High Roller: The Stu Ungar Story"},
{"movie_genre":"Comedy|Crime|Drama|Mystery|Thriller","movie_title":"Dead Men Tell"},
{"movie_genre":"Comedy|Crime|Thriller","movie_title":"Snatch"},
{"movie_genre":"Action","movie_title":"Punisher, The"},
{"movie_genre":"Drama","movie_title":"Story of Xinghua, The (Xinghua san yue tian)"},
{"movie_genre":"Drama|Horror","movie_title":"Cry Baby Lane"},
{"movie_genre":"Drama","movie_title":"Tyler Perry's For Colored Girls"},
{"movie_genre":"Crime|Horror|Romance","movie_title":"Beast from Haunted Cave"},
{"movie_genre":"Comedy","movie_title":"Captain's Paradise, The"},
{"movie_genre":"Action|Drama|Western","movie_title":"Back in the Saddle (Back in the Saddle Again)"},
{"movie_genre":"Comedy","movie_title":"Ping Pong Summer"},
{"movie_genre":"Documentary","movie_title":"Killer at Large"},
{"movie_genre":"Comedy","movie_title":"Johnny Be Good"},
{"movie_genre":"Action|Crime|Mystery|Romance|Thriller","movie_title":"Big Easy, The"},
{"movie_genre":"Drama|Romance","movie_title":"Whirlygirl"},
{"movie_genre":"Documentary","movie_title":"Sharkwater"},
{"movie_genre":"Documentary","movie_title":"Girlhood"},
{"movie_genre":"Documentary","movie_title":"A Night at the Movies: The Suspenseful World of Thrillers"},
{"movie_genre":"Adventure","movie_title":"Prince Valiant"},
{"movie_genre":"Drama","movie_title":"61*"},
{"movie_genre":"Drama|Romance|Thriller","movie_title":"Take My Eyes (Te doy mis ojos)"},
{"movie_genre":"Drama|Thriller","movie_title":"Clearing, The"},
{"movie_genre":"Crime|Mystery|Thriller","movie_title":"Plot of Fear"},
{"movie_genre":"Comedy","movie_title":"Whitecoats"},
{"movie_genre":"Crime|Drama","movie_title":"Drugstore Cowboy"},
{"movie_genre":"Comedy","movie_title":"Aziz Ansari: Buried Alive"},
{"movie_genre":"Horror|Thriller","movie_title":"Psycho III"},
{"movie_genre":"Drama|Romance","movie_title":"I Love You Too (Ik ook Van Jou)"},
{"movie_genre":"Crime|Drama|Thriller","movie_title":"Delusion"},
{"movie_genre":"Adventure|Children","movie_title":"Flipper"},
{"movie_genre":"Action|Adventure|Animation|Drama","movie_title":"Fullmetal Alchemist the Movie: Conqueror of Shamballa (Gekijô-ban hagane no renkinjutsushi: Shanbara wo yuku mono)"},
{"movie_genre":"Documentary","movie_title":"Ballad of the Little Soldier (Ballade vom kleinen Soldaten)"},
{"movie_genre":"Crime|Drama|Mystery","movie_title":"Jesse Stone: Stone Cold"},
{"movie_genre":"Horror|War","movie_title":"Revolt of the Zombies"},
{"movie_genre":"Drama","movie_title":"Elles"},
{"movie_genre":"Documentary","movie_title":"Madagascar"},
{"movie_genre":"Drama","movie_title":"Locke"},
{"movie_genre":"Documentary","movie_title":"Orderly or Disorderly (Be Tartib ya Bedoun-e Tartib)"},
{"movie_genre":"Comedy|Drama","movie_title":"Matinee"},
{"movie_genre":"Action|Drama|Thriller","movie_title":"Hostile Intentions"},
{"movie_genre":"Adventure|Comedy|Musical","movie_title":"Pirates of Penzance, The"},
{"movie_genre":"Action|IMAX","movie_title":"Man of Tai Chi"},
{"movie_genre":"Action|Adventure|Fantasy","movie_title":"Pirates of the Caribbean: Dead Man's Chest"},
{"movie_genre":"Drama","movie_title":"Woyzeck"},
{"movie_genre":"Comedy","movie_title":"Confessions of a Driving Instructor"},
{"movie_genre":"Adventure|Animation|Comedy|Western","movie_title":"Luke and Lucy: The Texas Rangers (Suske en Wiske: De Texas rakkers)"},
{"movie_genre":"Horror","movie_title":"Bones"},
{"movie_genre":"Comedy","movie_title":"Critical Condition"},
{"movie_genre":"Comedy|Drama|Romance","movie_title":"Tyler Perry's Diary of a Mad Black Woman"},
{"movie_genre":"Comedy","movie_title":"Sumo Do, Sumo Don't (Shiko funjatta)"},
{"movie_genre":"Comedy|Drama","movie_title":"Dark Habits (Entre tinieblas)"},
{"movie_genre":"Drama|Horror|Mystery|Thriller","movie_title":"Quarantine"},
{"movie_genre":"Comedy","movie_title":"Upstairs and Downstairs"},
{"movie_genre":"Action|War","movie_title":"Duellists, The"},
{"movie_genre":"Comedy|Crime|Drama|Romance","movie_title":"Edukators, The (Die Fetten Jahre sind vorbei)"},
{"movie_genre":"Mystery|Thriller","movie_title":"The Phantom Light"},
{"movie_genre":"Action|Adventure|Animation|Fantasy","movie_title":"Yu-Gi-Oh!"},
{"movie_genre":"Crime|Thriller","movie_title":"Small Town Murder Songs"},
{"movie_genre":"Action|Horror","movie_title":"Alone in the Dark II"},
{"movie_genre":"Drama","movie_title":"Believer, The"},
{"movie_genre":"Comedy|Musical","movie_title":"West Point Story, The"},
{"movie_genre":"Comedy","movie_title":"Anger Management"},
{"movie_genre":"Drama","movie_title":"Angel of Mine (a.k.a. The Mark of an Angel) (L'empreinte de l'ange)"},
{"movie_genre":"Horror|Thriller","movie_title":"13 Sins"},
{"movie_genre":"Action|Adventure|Sci-Fi","movie_title":"Superman"},
{"movie_genre":"Comedy|Drama","movie_title":"Love and Death on Long Island"},
{"movie_genre":"Action|Adventure|Comedy","movie_title":"Casino Royale"},
{"movie_genre":"Comedy|Drama","movie_title":"Second Civil War, The"},
{"movie_genre":"Drama|War","movie_title":"Ascent, The (Voskhozhdeniye)"},
{"movie_genre":"Thriller","movie_title":"Criminal Law"},
{"movie_genre":"Horror|Mystery|Thriller","movie_title":"Scream of Fear (a.k.a. Taste of Fear)"},
{"movie_genre":"Comedy|Crime","movie_title":"We're No Angels"},
{"movie_genre":"Drama","movie_title":"Of Mice and Men"},
{"movie_genre":"Drama","movie_title":"Bottle Shock"},
{"movie_genre":"Drama","movie_title":"Young Cassidy"},
{"movie_genre":"Action|Drama|Thriller","movie_title":"Air Crew"},
{"movie_genre":"Comedy|Musical|Romance","movie_title":"Spring is Here"},
{"movie_genre":"Horror|Mystery","movie_title":"Children of the Corn 666: Isaac's Return"},
{"movie_genre":"Documentary","movie_title":"Dreams on Spec"},
{"movie_genre":"Action|Adventure|Sci-Fi","movie_title":"Arrival II"},
{"movie_genre":"Animation|Children","movie_title":"Casper's Haunted Christmas"},
{"movie_genre":"Action|Adventure|Fantasy","movie_title":"Sorceress"},
{"movie_genre":"Crime|Horror|Thriller","movie_title":"Saw IV"},
{"movie_genre":"Adventure|Fantasy|Romance|Sci-Fi|Thriller","movie_title":"King Kong"},
{"movie_genre":"Documentary","movie_title":"Tank on the Moon"},
{"movie_genre":"Comedy|Western","movie_title":"Catlow"},
{"movie_genre":"Horror|Thriller","movie_title":"Children of the Corn: Revelation"},
{"movie_genre":"Comedy|Drama","movie_title":"Odette Toulemonde"},
{"movie_genre":"Drama","movie_title":"Salaam Bombay!"},
{"movie_genre":"Drama|Thriller","movie_title":"Tinker, Tailor, Soldier, Spy"},
{"movie_genre":"Drama|Thriller","movie_title":"Agnosia"},
{"movie_genre":"Animation|Comedy|Fantasy","movie_title":"Triplets of Belleville, The (Les triplettes de Belleville)"},
{"movie_genre":"Drama","movie_title":"Last Letter, The (La dernière lettre)"},
{"movie_genre":"Action|Sci-Fi|Thriller|IMAX","movie_title":"I Am Number Four"},
{"movie_genre":"Action|Crime|Drama|Thriller","movie_title":"Assault on Precinct 13"},
{"movie_genre":"Drama","movie_title":"Weekend (a.k.a. Le Week-end) (Week End)"},
{"movie_genre":"Crime|Drama","movie_title":"Yards, The"},
{"movie_genre":"Documentary","movie_title":"Do We Really Need the Moon?"},
{"movie_genre":"Comedy|Fantasy","movie_title":"Going Postal"},
{"movie_genre":"Action|Animation|Children|Comedy","movie_title":"Kung Fu Panda: Secrets of the Furious Five"},
{"movie_genre":"Drama","movie_title":"Searching for Bobby Fischer"},
{"movie_genre":"Crime|Drama|Romance","movie_title":"Pépé le Moko"},
{"movie_genre":"Drama","movie_title":"Machuca"},
{"movie_genre":"Crime|Horror|Mystery","movie_title":"Phantom of the Rue Morgue"},
{"movie_genre":"Drama|Mystery|Thriller","movie_title":"No Way Out"},
{"movie_genre":"Comedy|Drama","movie_title":"Mrs. Doubtfire"},
{"movie_genre":"Drama","movie_title":"Last Days"},
{"movie_genre":"Action|Adventure","movie_title":"Fled"},
{"movie_genre":"Action|Adventure|Thriller","movie_title":"Chain Reaction"},
{"movie_genre":"Action","movie_title":"Shadow Man"},
{"movie_genre":"Adventure","movie_title":"Treasure Island"},
{"movie_genre":"Drama","movie_title":"Solas"},
{"movie_genre":"Drama","movie_title":"Coming Down the Mountain"},
{"movie_genre":"Drama|Romance|War","movie_title":"Edge of Love, The"},
{"movie_genre":"Comedy|Crime|Horror|Thriller","movie_title":"Cottage, The"},
{"movie_genre":"Adventure|Animation|Children|Comedy","movie_title":"Lion King 1½, The"},
{"movie_genre":"Comedy|Drama|Romance","movie_title":"Toi et Moi"},
{"movie_genre":"Comedy","movie_title":"Sin of Harold Diddlebock, The"},
{"movie_genre":"Documentary","movie_title":"Louise Brooks: Looking for Lulu"},
{"movie_genre":"Fantasy|Sci-Fi","movie_title":"The Inhabited Island"},
{"movie_genre":"Documentary","movie_title":"My Flesh and Blood"},
{"movie_genre":"Crime|Drama|Mystery|Romance|Thriller","movie_title":"Double Hour, The (La doppia ora)"},
{"movie_genre":"Drama","movie_title":"Blue Angel, The (Blaue Engel, Der)"},
{"movie_genre":"Drama|Mystery|Thriller","movie_title":"8MM 2"},
{"movie_genre":"Drama","movie_title":"Glowing Stars"},
{"movie_genre":"Comedy|Horror","movie_title":"Big Bad Wolf"},
{"movie_genre":"Documentary","movie_title":"People vs. George Lucas, The"},
{"movie_genre":"Drama","movie_title":"Morvern Callar"},
{"movie_genre":"Drama|Romance|Sci-Fi","movie_title":"Miracle Mile"},
{"movie_genre":"Comedy","movie_title":"Die Weihnachtsklempner"},
{"movie_genre":"Documentary","movie_title":"In God We Teach"},
{"movie_genre":"Comedy|Drama|Romance","movie_title":"I Like It Like That"},
{"movie_genre":"Comedy|Romance","movie_title":"100 Girls"},
{"movie_genre":"Comedy","movie_title":"Lover's Knot"},
{"movie_genre":"Children|Comedy","movie_title":"Adventures of Elmo in Grouchland, The"},
{"movie_genre":"Drama|War","movie_title":"Paisan (Paisà)"},
{"movie_genre":"Documentary|Horror","movie_title":"Document of the Dead"},
{"movie_genre":"Drama","movie_title":"Dancing in the Rain (Ples v dezju)"},
{"movie_genre":"Horror|Sci-Fi","movie_title":"Werewolf, The"},
{"movie_genre":"Drama|Mystery","movie_title":"Equus"},
{"movie_genre":"Drama|Romance|War","movie_title":"Aimée & Jaguar"},
{"movie_genre":"Documentary","movie_title":"Photos in the City of Sylvia (Unas fotos en la ciudad de Sylvia)"},
{"movie_genre":"Drama|War","movie_title":"Under Ten Flags"},
{"movie_genre":"Comedy|Romance","movie_title":"Just a Gigolo"},
{"movie_genre":"Documentary","movie_title":"Koumiko Mystery, The (Mystère Koumiko, Le)"},
{"movie_genre":"Adventure|Comedy|Sci-Fi","movie_title":"Hitch Hikers Guide to the Galaxy, The"},
{"movie_genre":"Comedy|Drama|Musical","movie_title":"Band Baaja Baaraat"},
{"movie_genre":"Drama|Thriller","movie_title":"Fan, The"},
{"movie_genre":"Drama","movie_title":"Silent Light (Stellet licht)"},
{"movie_genre":"(no genres listed)","movie_title":"In Order Not to Be Here"},
{"movie_genre":"Thriller","movie_title":"El Lobo"},
{"movie_genre":"Comedy","movie_title":"Soap and Water"},
{"movie_genre":"Crime|Documentary","movie_title":"Lost for Life"},
{"movie_genre":"Comedy","movie_title":"Farmer & Chase"},
{"movie_genre":"Comedy","movie_title":"Dead Tired (Grosse Fatigue)"},
{"movie_genre":"Comedy|Drama","movie_title":"Preaching to the Perverted"},
{"movie_genre":"Action|Crime|Drama|Thriller","movie_title":"Boondock Saints II: All Saints Day, The"},
{"movie_genre":"Western","movie_title":"Tall T, The"},
{"movie_genre":"Comedy","movie_title":"Love God?, The"},
{"movie_genre":"Comedy|Drama|Thriller","movie_title":"Dealing: Or the Berkeley-to-Boston Forty-Brick Lost-Bag Blues"},
{"movie_genre":"Comedy|Drama","movie_title":"Biloxi Blues"},
{"movie_genre":"Action|Drama|Thriller","movie_title":"Sonny Boy"},
{"movie_genre":"Drama|Romance","movie_title":"Painted Veil, The"},
{"movie_genre":"Action|Adventure|Children|Comedy|Sci-Fi","movie_title":"Honey, We Shrunk Ourselves"},
{"movie_genre":"Action|Adventure|Animation|Sci-Fi","movie_title":"Akira"},
{"movie_genre":"Drama|Romance","movie_title":"Suzanne's Diary for Nicholas"},
{"movie_genre":"Action|Comedy|Romance|Thriller","movie_title":"So Close (Chik Yeung Tin Sai)"},
{"movie_genre":"Documentary","movie_title":"Great Stone Face, The"},
{"movie_genre":"Sci-Fi|Thriller","movie_title":"Europa Report"},
{"movie_genre":"Comedy|Drama","movie_title":"Meet John Doe"},
{"movie_genre":"Action|Adventure|Animation|Fantasy|Horror","movie_title":"Berserk: The Golden Age Arc - The Egg of the King"},
{"movie_genre":"Drama|Romance","movie_title":"Dying Young"},
{"movie_genre":"Documentary","movie_title":"Blank City"},
{"movie_genre":"Drama|Thriller|War","movie_title":"Soldier of Orange (a.k.a. Survival Run) (Soldaat van Oranje)"},
{"movie_genre":"Drama","movie_title":"Late Bloomers"},
{"movie_genre":"Action|Drama","movie_title":"Merantau"},
{"movie_genre":"Horror|Mystery","movie_title":"Ringu 2 (Ring 2)"},
{"movie_genre":"Horror|Thriller","movie_title":"Broken"},
{"movie_genre":"Action|Comedy","movie_title":"Men at Work"},
{"movie_genre":"Drama","movie_title":"Blind Mountain (Mang shan)"},
{"movie_genre":"Drama","movie_title":"Eight Miles High (Das wilde Leben)"},
{"movie_genre":"Action|Horror|Sci-Fi|War","movie_title":"Starship Troopers 2: Hero of the Federation"},
{"movie_genre":"Documentary","movie_title":"America's Heart and Soul"},
{"movie_genre":"Comedy|Horror","movie_title":"Rabid Grannies (Mémés cannibales, Les)"},
{"movie_genre":"Comedy","movie_title":"Incredible Burt Wonderstone, The"},
{"movie_genre":"Drama|War","movie_title":"Abraham Lincoln"},
{"movie_genre":"Drama","movie_title":"Strangers When We Meet"},
{"movie_genre":"Drama","movie_title":"Legend of Rita, The (Stille nach dem Schuß, Die)"},
{"movie_genre":"Drama","movie_title":"Mooz-lum"},
{"movie_genre":"Drama|Thriller","movie_title":"When the Bough Breaks"},
{"movie_genre":"Action|Adventure|Drama|Thriller","movie_title":"Gold"},
{"movie_genre":"Drama|Romance","movie_title":"Dangerous Liaisons"},
{"movie_genre":"Horror","movie_title":"Dracula"},
{"movie_genre":"Drama","movie_title":"Bleak House"},
{"movie_genre":"Adventure|Western","movie_title":"Mountain Men, The"},
{"movie_genre":"Comedy","movie_title":"Soul Kitchen"},
{"movie_genre":"Drama|Fantasy|Mystery","movie_title":"Lady in the Water"},
{"movie_genre":"Comedy","movie_title":"Ernest Scared Stupid"},
{"movie_genre":"Documentary","movie_title":"Style Wars"},
{"movie_genre":"Action|Crime|Drama|Thriller","movie_title":"Assault on Precinct 13"},
{"movie_genre":"Horror|Thriller","movie_title":"Nurse 3D"},
{"movie_genre":"Drama|IMAX","movie_title":"Aftershock (Tangshan dadizhen)"},
{"movie_genre":"Documentary","movie_title":"Glorious Technicolor"},
{"movie_genre":"Horror","movie_title":"Greystone Park"},
{"movie_genre":"Adventure|Comedy","movie_title":"Asterix & Obelix: God Save Britannia (Astérix et Obélix: Au service de Sa Majesté)"},
{"movie_genre":"Action|Adventure|Drama","movie_title":"Tomorrow, When the War Began"},
{"movie_genre":"Crime|Romance|Thriller","movie_title":"B. Monkey"},
{"movie_genre":"Action|Adventure|Drama","movie_title":"Shogun's Ninja (Ninja bugeicho momochi sandayu)"},
{"movie_genre":"Drama","movie_title":"Zero Years, The"},
{"movie_genre":"Adventure|Drama","movie_title":"Antarctica"},
{"movie_genre":"Adventure|Sci-Fi","movie_title":"The Mysterious Island"},
{"movie_genre":"Documentary","movie_title":"How to Make Money Selling Drugs"},
{"movie_genre":"Drama|Thriller","movie_title":"Niagara"},
{"movie_genre":"Action|Crime|Thriller","movie_title":"Direct Action"},
{"movie_genre":"Drama","movie_title":"Liz & Dick "},
{"movie_genre":"Action","movie_title":"Under Siege 2: Dark Territory"},
{"movie_genre":"Comedy|Drama","movie_title":"Soulless"},
{"movie_genre":"Comedy","movie_title":"Welcome to Mooseport"},
{"movie_genre":"Comedy|Fantasy","movie_title":"Canterville Ghost, The"},
{"movie_genre":"Comedy","movie_title":"Guide for the Married Man, A"},
{"movie_genre":"Drama","movie_title":"Music Room, The (Jalsaghar)"},
{"movie_genre":"Crime|Horror|Mystery","movie_title":"Murders in the Zoo"},
{"movie_genre":"Drama|Romance","movie_title":"Eccentricities of a Blonde-haired Girl (Singularidades de uma Rapariga Loura)"},
{"movie_genre":"Drama|Western","movie_title":"Time to Die (Tiempo de morir)"},
{"movie_genre":"Crime|Drama","movie_title":"Cry of the City"},
{"movie_genre":"Action|Adventure|Drama|Thriller|War","movie_title":"Centurion"},
{"movie_genre":"Comedy|Crime|Drama","movie_title":"Pigs and Battleships (Hogs and Warships) (The Flesh Is Hot) (Buta to gunkan)"},
{"movie_genre":"Drama|Fantasy|Sci-Fi","movie_title":"Avalon"},
{"movie_genre":"Comedy|Drama|Romance","movie_title":"Café Metropole"},
{"movie_genre":"Crime|Drama|Film-Noir|Romance","movie_title":"The Face Behind the Mask"},
{"movie_genre":"Comedy|Romance","movie_title":"Strawberry Blonde, The"},
{"movie_genre":"Thriller","movie_title":"Spartan"},
{"movie_genre":"Drama|Romance","movie_title":"My Rainy Days"},
{"movie_genre":"Drama","movie_title":"Man for All Seasons, A"},
{"movie_genre":"Drama","movie_title":"Star Maker, The (Uomo delle stelle, L')"},
{"movie_genre":"Crime|Thriller","movie_title":"Century of the Dragon (Long zai bian yuan)"},
{"movie_genre":"Documentary","movie_title":"Riding Giants"},
{"movie_genre":"Sci-Fi","movie_title":"Sol "},
{"movie_genre":"Crime|Horror|Thriller","movie_title":"Psycho"},
{"movie_genre":"Crime|Drama","movie_title":"Road to Perdition"},
{"movie_genre":"Comedy|Documentary","movie_title":"This Filthy World"},
{"movie_genre":"Crime|Drama","movie_title":"True Confessions"},
{"movie_genre":"Drama|Musical","movie_title":"Cadillac Records"},
{"movie_genre":"Crime|Drama|Mystery","movie_title":"Endeavour"},
{"movie_genre":"Documentary","movie_title":"Fellini: I'm a Born Liar (Fellini: Je Suis um Grand Menteur)"},
{"movie_genre":"Action|Adventure|Animation|Comedy|Crime|Mystery","movie_title":"Lupin III: The Castle Of Cagliostro (Rupan sansei: Kariosutoro no shiro)"},
{"movie_genre":"Drama|Romance","movie_title":"Eternal Return, The (L'éternel retour)"},
{"movie_genre":"Documentary","movie_title":"Sofia's Last Ambulance (Poslednaka lineika na Sofia)"},
{"movie_genre":"Drama","movie_title":"Ghosts (Gespenster)"},
{"movie_genre":"Crime|Drama|Film-Noir","movie_title":"Rogue Cop"},
{"movie_genre":"Drama|War","movie_title":"Midway"},
{"movie_genre":"Drama|Romance","movie_title":"The Fault in Our Stars"},
{"movie_genre":"Comedy|Musical|Romance","movie_title":"Tea For Two"},
{"movie_genre":"Western","movie_title":"Man from Laramie, The"},
{"movie_genre":"Drama|Musical|Romance","movie_title":"How Green Was My Valley"},
{"movie_genre":"Drama|Sci-Fi|Thriller","movie_title":"Virtuality"},
{"movie_genre":"Drama","movie_title":"7 Days in Havana"},
{"movie_genre":"Drama","movie_title":"Tarda estate"},
{"movie_genre":"Drama","movie_title":"Toronto Stories"},
{"movie_genre":"Drama|Romance|Thriller|War","movie_title":"Quiet American, The"},
{"movie_genre":"Comedy|Romance","movie_title":"Carnival in Flanders (La kermesse héroïque)"},
{"movie_genre":"Action|Western","movie_title":"Fistful of Dollars, A (Per un pugno di dollari)"},
{"movie_genre":"Comedy|Drama","movie_title":"Diner"},
{"movie_genre":"Drama|Fantasy|Horror","movie_title":"White Reindeer, The (Valkoinen peura)"},
{"movie_genre":"Drama","movie_title":"This is Our Time"},
{"movie_genre":"Drama|War","movie_title":"Man Who Never Was, The"},
{"movie_genre":"Comedy","movie_title":"Strangers with Candy"},
{"movie_genre":"Action|Crime|Drama","movie_title":"Vigilante"},
{"movie_genre":"Drama|Romance","movie_title":"Stranger by the Lake (L'inconnu du lac)"},
{"movie_genre":"Comedy|Romance","movie_title":"Black Cat, White Cat (Crna macka, beli macor)"},
{"movie_genre":"Western","movie_title":"Man Called Gannon, A"},
{"movie_genre":"Drama","movie_title":"Trucker"},
{"movie_genre":"Comedy|Drama","movie_title":"Revenge for Jolly!"},
{"movie_genre":"Drama|War","movie_title":"Nothing Personal"},
{"movie_genre":"Comedy","movie_title":"Who's Your Caddy?"},
{"movie_genre":"Drama|Horror","movie_title":"Queen of Spades, The"},
{"movie_genre":"Action|Thriller","movie_title":"Enemy of the State"},
{"movie_genre":"Comedy|Mystery","movie_title":"Murder on a Honeymoon"},
{"movie_genre":"Animation","movie_title":"Blue Umbrella, The"},
{"movie_genre":"Adventure|Comedy|Fantasy","movie_title":"Hook"},
{"movie_genre":"Animation|Comedy","movie_title":"Daria: Is It Fall Yet?"},
{"movie_genre":"Horror|Mystery|Thriller","movie_title":"Munger Road"},
{"movie_genre":"Horror|Mystery|Thriller","movie_title":"Nightmare"},
{"movie_genre":"Comedy|Drama","movie_title":"Married to It"},
{"movie_genre":"Drama","movie_title":"7 Women (a.k.a. Seven Women)"},
{"movie_genre":"Documentary","movie_title":"Make Believe"},
{"movie_genre":"Horror|Thriller","movie_title":"Raising Cain"},
{"movie_genre":"Fantasy|IMAX","movie_title":"Cirque du Soleil: Worlds Away"},
{"movie_genre":"Crime|Horror|Thriller","movie_title":"Psycho"},
{"movie_genre":"Drama|Fantasy","movie_title":"Christmas Carol, A"},
{"movie_genre":"Drama","movie_title":"Dancing at Lughnasa"},
{"movie_genre":"Crime|Drama","movie_title":"I Love Trouble"},
{"movie_genre":"Western","movie_title":"Decision at Sundown"},
{"movie_genre":"Action|Comedy","movie_title":"Flashback"},
{"movie_genre":"Drama","movie_title":"The Lost Prince"},
{"movie_genre":"Drama|Romance","movie_title":"Passion Play"},
{"movie_genre":"Western","movie_title":"Doc"},
{"movie_genre":"War","movie_title":"Prisoner of the Mountains (Kavkazsky plennik)"},
{"movie_genre":"Horror|Sci-Fi","movie_title":"Xtro 2: The Second Encounter"},
{"movie_genre":"Documentary","movie_title":"Louise Brooks: Looking for Lulu"},
{"movie_genre":"Action|Comedy","movie_title":"Kopps"},
{"movie_genre":"Comedy|Drama","movie_title":"Faat Kiné"},
{"movie_genre":"Adventure|Drama","movie_title":"Warrior, The"},
{"movie_genre":"Children|Comedy","movie_title":"Princess for Christmas, A"},
{"movie_genre":"Action|Adventure|Thriller","movie_title":"Captain Midnight"},
{"movie_genre":"Drama|Film-Noir|Thriller","movie_title":"Wrong Man, The"},
{"movie_genre":"Comedy|Drama","movie_title":"If I Were You"},
{"movie_genre":"Drama","movie_title":"Color of Paradise, The (Rang-e khoda)"},
{"movie_genre":"Comedy|Drama|Romance","movie_title":"Shanghai Calling"},
{"movie_genre":"Comedy|Romance","movie_title":"Lucky Break (a.k.a. Paperback Romance)"},
{"movie_genre":"Comedy|Horror|Mystery|Sci-Fi","movie_title":"Stuff, The"},
{"movie_genre":"Documentary","movie_title":"Best Boy"},
{"movie_genre":"Comedy|Mystery","movie_title":"Once Upon a Crime..."},
{"movie_genre":"Drama","movie_title":"Quand je serai petit"},
{"movie_genre":"Drama|Romance|War","movie_title":"Cranes Are Flying, The (Letyat zhuravli)"},
{"movie_genre":"Comedy|Drama|Romance","movie_title":"Good Year, A"},
{"movie_genre":"Romance|Thriller","movie_title":"Attack, The"},
{"movie_genre":"Drama|Western","movie_title":"Annie Oakley"},
{"movie_genre":"Comedy","movie_title":"Cinderfella"},
{"movie_genre":"Comedy|Drama|War","movie_title":"Tea with Mussolini"},
{"movie_genre":"Documentary","movie_title":"Louise Brooks: Looking for Lulu"},
{"movie_genre":"Action|Horror|Thriller","movie_title":"Piranha (Piranha 3D)"},
{"movie_genre":"Comedy","movie_title":"Death at a Funeral"},
{"movie_genre":"Comedy","movie_title":"Rocker, The"},
{"movie_genre":"Documentary","movie_title":"Happiness"},
{"movie_genre":"Drama|War","movie_title":"Hunters, The"},
{"movie_genre":"Comedy|Romance","movie_title":"Des gens qui s'embrassent"},
{"movie_genre":"Drama|Romance","movie_title":"Gabrielle"},
{"movie_genre":"Action|Drama|Fantasy","movie_title":"Bunraku"},
{"movie_genre":"Comedy","movie_title":"Adventurer, The"},
{"movie_genre":"Comedy|Drama","movie_title":"It Started in Naples"},
{"movie_genre":"Action|Adventure|Drama|Sci-Fi|Thriller","movie_title":"Sound of Thunder, A"},
{"movie_genre":"Action|Comedy|Crime|Drama","movie_title":"Lethal Weapon 3"},
{"movie_genre":"Drama","movie_title":"Maradona, the Hand of God (Maradona, la mano di Dio)"},
{"movie_genre":"Horror","movie_title":"Killjoy"},
{"movie_genre":"Action|Adventure|Animation|Children|Fantasy","movie_title":"Bionicle 2: Legends of Metru Nui"},
{"movie_genre":"Drama|Musical|Thriller","movie_title":"Psych-Out"},
{"movie_genre":"Drama|Romance","movie_title":"Casablanca"},
{"movie_genre":"Drama|Romance","movie_title":"White Massai, The (Weisse Massai, Die)"},
{"movie_genre":"Documentary|Drama|War","movie_title":"War Game, The"},
{"movie_genre":"Drama|Horror","movie_title":"Wishing Stairs (Yeogo goedam 3: Yeowoo gyedan)"},
{"movie_genre":"Crime|Drama","movie_title":"River's Edge"},
{"movie_genre":"Action|Adventure","movie_title":"Allan Quatermain and the Temple of Skulls"},
{"movie_genre":"Action|Adventure|Crime","movie_title":"Tiger Brigades, The (Les brigades du Tigre)"},
{"movie_genre":"Drama|Romance","movie_title":"Tender Comrade"},
{"movie_genre":"Action|Adventure|Animation","movie_title":"Dragon Ball Z: Cooler's Revenge (Doragon bôru Z 5: Tobikkiri no saikyô tai saikyô)"},
{"movie_genre":"Action|Crime|Drama|IMAX","movie_title":"Dark Knight, The"},
{"movie_genre":"Drama","movie_title":"Harmful Insect (Gaichu)"},
{"movie_genre":"Drama","movie_title":"Ego"},
{"movie_genre":"Sci-Fi","movie_title":"Sol "},
{"movie_genre":"Drama","movie_title":"Oscar and the Lady in Pink"},
{"movie_genre":"Drama|Thriller","movie_title":"Fear Me Not (Den du frygter)"},
{"movie_genre":"Children|Fantasy","movie_title":"Fishtales"},
{"movie_genre":"Horror|Sci-Fi","movie_title":"Beast of Yucca Flats, The"},
{"movie_genre":"Comedy|Horror|Thriller","movie_title":"Lost Boys: The Tribe"},
{"movie_genre":"Comedy|Drama|Musical|Romance","movie_title":"Destiny (Al-massir)"},
{"movie_genre":"Drama","movie_title":"Songs From the Second Floor (Sånger från andra våningen)"},
{"movie_genre":"Comedy|Drama|Romance","movie_title":"Just Buried"},
{"movie_genre":"War","movie_title":"Brother's War"},
{"movie_genre":"Drama","movie_title":"Diary of a Nymphomaniac (Diario de una Ninfómana)"},
{"movie_genre":"Action|Comedy","movie_title":"New Kids Turbo"},
{"movie_genre":"Action|Mystery|Sci-Fi","movie_title":"Star Trek VI: The Undiscovered Country"},
{"movie_genre":"Comedy|Drama","movie_title":"Suddenly (Tan de Repente)"},
{"movie_genre":"Comedy","movie_title":"Brewster McCloud"},
{"movie_genre":"Drama|Film-Noir|Thriller","movie_title":"Big Night, The"},
{"movie_genre":"Comedy|Crime","movie_title":"Sister Act"},
{"movie_genre":"Sci-Fi","movie_title":"Earth vs. the Flying Saucers"},
{"movie_genre":"Adventure|Children|Comedy|Drama","movie_title":"For the Love of Benji"},
{"movie_genre":"Comedy|Romance","movie_title":"Boy Meets Girl"},
{"movie_genre":"Horror","movie_title":"Hood of the Living Dead"},
{"movie_genre":"Action|Mystery|Thriller","movie_title":"Hidden Agenda"},
{"movie_genre":"Comedy|Romance","movie_title":"Allnighter, The"},
{"movie_genre":"Thriller","movie_title":"Safe House"},
{"movie_genre":"Drama|Musical","movie_title":"Jesus Christ Superstar"},
{"movie_genre":"Animation|Comedy","movie_title":"Flushed Away"},
{"movie_genre":"Documentary|Sci-Fi","movie_title":"The Captains"},
{"movie_genre":"Drama|Musical|Romance","movie_title":"Aashiqui 2"},
{"movie_genre":"Animation","movie_title":"Hand, The (Ruka)"},
{"movie_genre":"Comedy","movie_title":"3, 2, 1... Frankie Go Boom (Frankie Go Boom)"},
{"movie_genre":"Crime|Drama","movie_title":"Killer: A Journal of Murder"},
{"movie_genre":"Comedy|Romance","movie_title":"I Give It a Year"},
{"movie_genre":"Action|Adventure|Drama|Thriller","movie_title":"Colombiana"},
{"movie_genre":"Drama","movie_title":"Mandabi (The Money Order)"},
{"movie_genre":"Adventure|Comedy|Documentary|Fantasy","movie_title":"Introduction to Physics, An"},
{"movie_genre":"Action|Adventure|Drama|War","movie_title":"Great Escape, The"},
{"movie_genre":"Drama","movie_title":"Lacombe Lucien"},
{"movie_genre":"Action|Adventure|Comedy|War","movie_title":"Escape to Athena"},
{"movie_genre":"Adventure|Sci-Fi","movie_title":"Star Trek: The Motion Picture"},
{"movie_genre":"Drama","movie_title":"In the City (En la ciudad)"},
{"movie_genre":"Action|Romance|Western","movie_title":"Star Packer, The"},
{"movie_genre":"Drama|Thriller|War","movie_title":"Bedford Incident, The"},
{"movie_genre":"Drama|Sci-Fi","movie_title":"Hey, Happy!"},
{"movie_genre":"Comedy|Romance","movie_title":"It"},
{"movie_genre":"Drama","movie_title":"Susannah of the Mounties"},
{"movie_genre":"Action|Adventure|Thriller","movie_title":"Tomorrow Never Dies"},
{"movie_genre":"Drama","movie_title":"Tungsten"},
{"movie_genre":"Horror","movie_title":"Bloodtide"},
{"movie_genre":"Comedy","movie_title":"Napoleon Dynamite"},
{"movie_genre":"Action|Adventure|Fantasy|Sci-Fi","movie_title":"Godzilla: Final Wars (Gojira: Fainaru uôzu)"},
{"movie_genre":"Comedy","movie_title":"Kummeli Goldrush (Kummeli kultakuume)"},
{"movie_genre":"Drama","movie_title":"Son of God"},
{"movie_genre":"Drama|Thriller","movie_title":"Black Sun (Kuroi taiyô)"},
{"movie_genre":"Drama|Romance","movie_title":"5x2"},
{"movie_genre":"Drama|Thriller","movie_title":"23 (23 - Nichts ist so wie es scheint)"},
{"movie_genre":"Drama","movie_title":"Aliyah (Alyah) "},
{"movie_genre":"Comedy|Western","movie_title":"My Name Is Nobody (Il Mio nome è Nessuno)"},
{"movie_genre":"Action|Adventure|Comedy","movie_title":"Lupin the 3rd"},
{"movie_genre":"Action|Drama|Thriller","movie_title":"Deadly Tower, The"},
{"movie_genre":"Action|Crime|Drama","movie_title":"Green Street Hooligans 2"},
{"movie_genre":"Comedy|Drama|Romance","movie_title":"Dances With the Dragons ( Yu long gong wu)"},
{"movie_genre":"Drama|Romance","movie_title":"Hours, The"},
{"movie_genre":"Action|Animation|Sci-Fi|Western","movie_title":"Trigun: Badlands Rumble"},
{"movie_genre":"Documentary","movie_title":"Sam Peckinpah's West: Legacy of a Hollywood Renegade"},
{"movie_genre":"Comedy|Drama|Mystery|Thriller","movie_title":"Silver City"},
{"movie_genre":"Comedy|Drama","movie_title":"Family Game, The (Kazoku gêmu)"},
{"movie_genre":"Drama","movie_title":"Griffin and Phoenix"},
{"movie_genre":"Comedy|Drama|Fantasy","movie_title":"Little Otik (Otesánek)"},
{"movie_genre":"Comedy|Crime|Drama|Thriller","movie_title":"Body Count"},
{"movie_genre":"Documentary|Fantasy","movie_title":"My Winnipeg"},
{"movie_genre":"Horror","movie_title":"Devil's Rain, The"},
{"movie_genre":"Comedy|Drama","movie_title":"Mr. North"},
{"movie_genre":"Adventure|Drama","movie_title":"Desperate Search"},
{"movie_genre":"Comedy|Drama","movie_title":"Divided We Fall (Musíme si pomáhat)"},
{"movie_genre":"Action|Drama","movie_title":"Bad Asses (Bad Ass 2)"},
{"movie_genre":"Drama","movie_title":"The Princess of Egypt"},
{"movie_genre":"Documentary","movie_title":"Cartoonist: Jeff Smith, BONE and the Changing Face of Comics, The"},
{"movie_genre":"Children|Comedy|Sci-Fi","movie_title":"Cat from Outer Space, The"},
{"movie_genre":"Horror|Mystery|Thriller","movie_title":"Ring, The"},
{"movie_genre":"Drama|Mystery|Romance","movie_title":"Sommersby"},
{"movie_genre":"Action|Adventure|Thriller","movie_title":"Broken Arrow"},
{"movie_genre":"Action|Drama|Thriller","movie_title":"Body of Lies"},
{"movie_genre":"Comedy","movie_title":"Rosalie Goes Shopping"},
{"movie_genre":"Documentary","movie_title":"I Want to Look Like That Guy"},
{"movie_genre":"Drama|Romance","movie_title":"City Girl"},
{"movie_genre":"Comedy","movie_title":"Soapdish"},
{"movie_genre":"Children|Fantasy","movie_title":"Snow Queen, The (Lumikuningatar)"},
{"movie_genre":"Children|Comedy|Musical","movie_title":"Muppet Family Christmas, A"},
{"movie_genre":"Drama","movie_title":"The Big One: The Great Los Angeles Earthquake"},
{"movie_genre":"Comedy","movie_title":"Soap and Water"},
{"movie_genre":"Comedy","movie_title":"Fun Size"},
{"movie_genre":"Documentary","movie_title":"As I Was Moving Ahead Occasionally I Saw Brief Glimpses of Beauty"},
{"movie_genre":"Documentary","movie_title":"Master of the Universe"},
{"movie_genre":"Comedy|Thriller","movie_title":"Zero 2"},
{"movie_genre":"Comedy","movie_title":"Cops"},
{"movie_genre":"Comedy|Drama|Mystery","movie_title":"Life of Another, The (La vie d'une autre)"},
{"movie_genre":"Action|Comedy|Romance|Western","movie_title":"Son of Paleface"},
{"movie_genre":"Documentary","movie_title":"Enemies of Reason, The"},
{"movie_genre":"Adventure|Comedy|Documentary|Mystery","movie_title":"Cowspiracy: The Sustainability Secret"},
{"movie_genre":"Drama|Romance","movie_title":"Man of the World"},
{"movie_genre":"Drama","movie_title":"Dr. Ehrlich's Magic Bullet"},
{"movie_genre":"Comedy","movie_title":"Bandit: Bandit's Silver Angel (Smokey and the Bandit 7) (Bandit: Bandit and the Silver Angel)"},
{"movie_genre":"Drama","movie_title":"Reluctant Fundamentalist, The"},
{"movie_genre":"Animation|Children|Comedy","movie_title":"Emperor's New Groove 2: Kronk's New Groove, The"},
{"movie_genre":"Documentary","movie_title":"Cross: The Arthur Blessitt Story, The"},
{"movie_genre":"Drama|Romance","movie_title":"My Brilliant Career"},
{"movie_genre":"Adventure|Drama|Fantasy","movie_title":"From Time to Time"},
{"movie_genre":"Comedy","movie_title":"Finger, The (Dedo, El)"},
{"movie_genre":"Horror|Sci-Fi|Thriller","movie_title":"Tentacles (Tentacoli)"},
{"movie_genre":"Documentary","movie_title":"Brandon Teena Story, The"},
{"movie_genre":"Documentary","movie_title":"Last Mountain, The"},
{"movie_genre":"Children|Comedy|Drama","movie_title":"Pollyanna"},
{"movie_genre":"Sci-Fi","movie_title":"Babylon 5"},
{"movie_genre":"Crime|Drama","movie_title":"Heavenly Creatures"},
{"movie_genre":"Documentary","movie_title":"John Huston: The Man, the Movies, the Maverick"},
{"movie_genre":"Drama","movie_title":"London"},
{"movie_genre":"Romance","movie_title":"Paradise"},
{"movie_genre":"Comedy|Musical|Romance","movie_title":"High Society"},
{"movie_genre":"Comedy","movie_title":"BFFs"},
{"movie_genre":"Documentary","movie_title":"Val Lewton:  The Man in the Shadows"},
{"movie_genre":"Drama","movie_title":"Five Minarets in New York (Act of Vengeance) (Terrorist, The)"},
{"movie_genre":"Mystery","movie_title":"Afterwards"},
{"movie_genre":"Comedy|Drama","movie_title":"All is Bright"},
{"movie_genre":"Drama|Thriller","movie_title":"Agnosia"},
{"movie_genre":"Comedy|Drama","movie_title":"One-Way Ticket to Mombasa (Menolippu Mombasaan)"},
{"movie_genre":"Drama","movie_title":"Autobiography of Miss Jane Pittman, The"},
{"movie_genre":"Documentary","movie_title":"Sister Helen "},
{"movie_genre":"Comedy|Crime","movie_title":"Striptease"},
{"movie_genre":"Adventure|Animation|Children|Comedy|Fantasy","movie_title":"Emperor's New Groove, The"},
{"movie_genre":"Comedy|Drama","movie_title":"Sorority Wars"},
{"movie_genre":"Horror","movie_title":"Living Skeleton, The (Kyûketsu dokuro-sen)"},
{"movie_genre":"Drama","movie_title":"Silence, The (Sokout)"},
{"movie_genre":"Crime|Drama|Thriller","movie_title":"Mississippi Burning"},
{"movie_genre":"Drama|Romance","movie_title":"Venus"},
{"movie_genre":"Crime|Drama|Mystery|Thriller","movie_title":"After Alice (Eye of the Killer)"},
{"movie_genre":"Comedy|Fantasy","movie_title":"Rookie of the Year"},
{"movie_genre":"Comedy|Drama|Musical|IMAX","movie_title":"Rock of Ages"},
{"movie_genre":"Horror|Thriller","movie_title":"Ward, The"},
{"movie_genre":"Drama","movie_title":"Eva (a.k.a. Eve)"},
{"movie_genre":"Adventure|Animation|Children","movie_title":"Dragon Hunters (Chasseurs de dragons)"},
{"movie_genre":"Comedy|Horror|Musical","movie_title":"Poultrygeist: Night of the Chicken Dead"},
{"movie_genre":"Drama|War","movie_title":"Big Lift, The"},
{"movie_genre":"Drama","movie_title":"Woman of Paris, A"},
{"movie_genre":"Comedy|Drama","movie_title":"Zombie and the Ghost Train (Zombie ja Kummitusjuna)"},
{"movie_genre":"Documentary","movie_title":"Human Family Tree, The"},
{"movie_genre":"Romance","movie_title":"Meet Joe Black"},
{"movie_genre":"Horror|Mystery","movie_title":"Sauna"},
{"movie_genre":"Drama","movie_title":"Interkosmos"},
{"movie_genre":"Thriller","movie_title":"Sexual Predator"},
{"movie_genre":"Comedy|Drama","movie_title":"Lars and the Real Girl"},
{"movie_genre":"Comedy|Drama|Horror|Romance|Thriller","movie_title":"Love Object"},
{"movie_genre":"Drama","movie_title":"We Live Again"},
{"movie_genre":"Animation|Fantasy","movie_title":"Snails, The (Escargots, Les)"},
{"movie_genre":"Comedy|Romance|War","movie_title":"Kiss Them for Me"},
{"movie_genre":"Crime|Documentary","movie_title":"Two Escobars, The"},
{"movie_genre":"Drama|Romance","movie_title":"Anna Karenina"},
{"movie_genre":"Action|Drama","movie_title":"Zatoichi and the Chest of Gold (Zatôichi senryô-kubi) (Zatôichi 6)"},
{"movie_genre":"Drama","movie_title":"Strike (Stachka)"},
{"movie_genre":"Action|Drama|War","movie_title":"Inescapable"},
{"movie_genre":"Drama|Romance|War","movie_title":"Peach Thief, The (Kradetzat na praskovi)"},
{"movie_genre":"Drama|Romance","movie_title":"Vincere"},
{"movie_genre":"Drama|Romance","movie_title":"Summer in February"},
{"movie_genre":"Action|Comedy|Crime","movie_title":"Silver Streak"},
{"movie_genre":"Children|Fantasy|Sci-Fi","movie_title":"Mac and Me"},
{"movie_genre":"Comedy|Drama","movie_title":"Smoke"},
{"movie_genre":"Action|Adventure|Sci-Fi","movie_title":"Jupiter Ascending"},
{"movie_genre":"Adventure|Musical","movie_title":"Huckleberry Finn"},
{"movie_genre":"Documentary","movie_title":"Below Sea Level"},
{"movie_genre":"Action|Adventure","movie_title":"Ambush (Mai fu)"},
{"movie_genre":"Comedy|Drama|Thriller","movie_title":"King Is Dead!, The"},
{"movie_genre":"Action|Animation|Sci-Fi","movie_title":"Avengers Confidential: Black Widow & Punisher"},
{"movie_genre":"Comedy|Crime|Mystery|Thriller","movie_title":"Clue"},
{"movie_genre":"Drama|Mystery","movie_title":"West of Zanzibar"},
{"movie_genre":"Action|Comedy|Romance|Western","movie_title":"Son of Paleface"},
{"movie_genre":"Horror|Thriller","movie_title":"Lights Out"},
{"movie_genre":"Comedy|Drama|Romance","movie_title":"Under the Roofs of Paris (Sous les toits de Paris)"},
{"movie_genre":"Horror|Sci-Fi","movie_title":"Brain, The"},
{"movie_genre":"Documentary","movie_title":"Manufactured Landscapes"},
{"movie_genre":"Comedy","movie_title":"All Over the Guy"},
{"movie_genre":"Action|Crime|Drama|Thriller","movie_title":"Cradle 2 the Grave"},
{"movie_genre":"Horror|Sci-Fi|Thriller","movie_title":"Pulse"},
{"movie_genre":"Comedy|Musical|War","movie_title":"Duck Soup"},
{"movie_genre":"Comedy|Romance","movie_title":"Listy do M."},
{"movie_genre":"Comedy|Drama","movie_title":"Mama's Boy"},
{"movie_genre":"Drama|Romance","movie_title":"How to Make an American Quilt"},
{"movie_genre":"Comedy","movie_title":"Scarecrow, The"},
{"movie_genre":"Drama","movie_title":"Wild Child, The (Enfant sauvage, L')"},
{"movie_genre":"Documentary","movie_title":"They Call Us Misfits (Dom kallar oss mods)"},
{"movie_genre":"Documentary","movie_title":"Card Subject To Change"},
{"movie_genre":"Drama|Romance","movie_title":"Dangerous Woman, A"},
{"movie_genre":"Drama|Musical|Romance","movie_title":"Listen to Your Heart"},
{"movie_genre":"Comedy","movie_title":"New Waterford Girl"},
{"movie_genre":"Crime|Drama","movie_title":"Mean Streets"},
{"movie_genre":"Children","movie_title":"Quatsch und die Nasenbärbande"},
{"movie_genre":"Comedy|Drama|Romance","movie_title":"Falling Up"},
{"movie_genre":"Drama|Thriller","movie_title":"Blindness"},
{"movie_genre":"Adventure|Drama|Romance|War","movie_title":"March or Die"},
{"movie_genre":"Adventure|Comedy|War","movie_title":"You Can't Win 'Em All"},
{"movie_genre":"Comedy|Drama","movie_title":"Tobacco Road"},
{"movie_genre":"Action|Adventure|Comedy","movie_title":"New York Minute"},
{"movie_genre":"Comedy|Crime|Mystery|Thriller","movie_title":"Clue"},
{"movie_genre":"Comedy|Drama|Romance","movie_title":"Edge of Seventeen"},
{"movie_genre":"Musical","movie_title":"Orchestra Wives"},
{"movie_genre":"Drama|Romance","movie_title":"Medicine for Melancholy"},
{"movie_genre":"Drama","movie_title":"American Soldier, The (Der amerikanische Soldat)"},
{"movie_genre":"Comedy","movie_title":"Sweet Liberty"},
{"movie_genre":"Action|Adventure","movie_title":"Good Man in Africa, A"},
{"movie_genre":"Adventure|Drama|Horror","movie_title":"Survival Island (Three)"},
{"movie_genre":"Action|Adventure|Drama|Thriller","movie_title":"Tracker"},
{"movie_genre":"Comedy|Drama","movie_title":"Cold Souls"},
{"movie_genre":"Horror|Thriller","movie_title":"Children of the Corn: Revelation"},
{"movie_genre":"Horror","movie_title":"Drive-In Horrorshow"},
{"movie_genre":"Comedy|Drama|Romance","movie_title":"Spanglish"},
{"movie_genre":"Crime|Drama|Romance|Thriller","movie_title":"Return to Paradise"},
{"movie_genre":"Drama","movie_title":"Wilson"},
{"movie_genre":"Crime|Drama|Romance","movie_title":"Little Thief, The (La petite voleuse)"},
{"movie_genre":"Comedy|Crime","movie_title":"First Sunday"},
{"movie_genre":"Drama|Horror|Mystery","movie_title":"Other, The"},
{"movie_genre":"Comedy|Drama","movie_title":"Vizontele Tuuba"},
{"movie_genre":"Documentary","movie_title":"Happy Birthday to a Beautiful Woman"},
{"movie_genre":"Drama|Romance","movie_title":"Between the Sheets (Entre Lençóis)"},
{"movie_genre":"Comedy|Drama","movie_title":"Being Flynn"},
{"movie_genre":"Drama|Romance","movie_title":"My Name is Khan"},
{"movie_genre":"Documentary","movie_title":"Apollo Zero"},
{"movie_genre":"Comedy|Drama|Romance","movie_title":"Roman Holiday"},
{"movie_genre":"Drama|Musical","movie_title":"Janie Jones"},
{"movie_genre":"Comedy","movie_title":"Tenure"},
{"movie_genre":"Action|Crime|Drama","movie_title":"Hidden Assassin (Shooter, The)"},
{"movie_genre":"Comedy|Sci-Fi|Thriller","movie_title":"Manhattan Project, The"},
{"movie_genre":"Action|Drama","movie_title":"Target"},
{"movie_genre":"Drama","movie_title":"Tic Code, The"},
{"movie_genre":"Horror","movie_title":"Nightmare on Elm Street 5: The Dream Child, A"},
{"movie_genre":"Horror|Thriller","movie_title":"Stepdaughter, The"},
{"movie_genre":"Crime|Drama","movie_title":"The Strange Affair"},
{"movie_genre":"Action|Thriller","movie_title":"Fear of Flying"},
{"movie_genre":"Comedy|Drama|Romance","movie_title":"Juha"},
{"movie_genre":"Adventure|Animation|Children|Fantasy","movie_title":"We're Back! A Dinosaur's Story"},
{"movie_genre":"Drama","movie_title":"Of Gods and Men (Des hommes et des dieux)"},
{"movie_genre":"Drama|Musical","movie_title":"Center Stage"},
{"movie_genre":"Comedy|Drama|Romance","movie_title":"2 Days in Paris"},
{"movie_genre":"Adventure|Drama|Sci-Fi","movie_title":"Day of the Doctor, The"},
{"movie_genre":"Drama|Thriller","movie_title":"When the Bough Breaks"},
{"movie_genre":"Comedy","movie_title":"It Runs in the Family (My Summer Story)"},
{"movie_genre":"Action|Sci-Fi|Thriller","movie_title":"X-Men: The Last Stand"},
{"movie_genre":"Action","movie_title":"Tracers"},
{"movie_genre":"Drama","movie_title":"Madame Bovary"},
{"movie_genre":"Horror|Thriller","movie_title":"Wrong Turn"},
{"movie_genre":"Thriller","movie_title":"388 Arletta Avenue"},
{"movie_genre":"Drama|Thriller","movie_title":"Compliance"},
{"movie_genre":"Comedy","movie_title":"Someone Marry Barry"},
{"movie_genre":"Musical","movie_title":"Battle of the Year"},
{"movie_genre":"Western","movie_title":"Shalako"},
{"movie_genre":"Action|Animation|Horror","movie_title":"Hellsing Ultimate OVA Series"},
{"movie_genre":"Musical|Romance","movie_title":"Broadway Melody of 1938"},
{"movie_genre":"Action|Adventure|Comedy|Romance","movie_title":"Mr. & Mrs. Smith"},
{"movie_genre":"Horror|Mystery|Thriller","movie_title":"The Damned"},
{"movie_genre":"Documentary","movie_title":"Who the Hell Is Juliette? (¿Quién diablos es Juliette?)"},
{"movie_genre":"Comedy","movie_title":"Cage aux Folles, La"},
{"movie_genre":"Comedy|Sci-Fi","movie_title":"Galaxina"},
{"movie_genre":"Documentary","movie_title":"When We Were Kings"},
{"movie_genre":"Comedy|Drama|Musical|Romance","movie_title":"Sweet Charity"},
{"movie_genre":"Documentary","movie_title":"Endless Summer, The"},
{"movie_genre":"Action|Crime|Drama","movie_title":"Yamakasi - Les samouraïs des temps modernes"},
{"movie_genre":"Action|Sci-Fi","movie_title":"Atomic Rulers of the World"},
{"movie_genre":"Children|Comedy|Fantasy","movie_title":"Dirt Bike Kid, The"},
{"movie_genre":"Drama","movie_title":"4"},
{"movie_genre":"Drama","movie_title":"Raisin in the Sun, A"},
{"movie_genre":"Drama","movie_title":"Marriage Material"},
{"movie_genre":"Comedy","movie_title":"Play House, The"},
{"movie_genre":"Children|Comedy|Drama|Musical","movie_title":"Rebecca of Sunnybrook Farm"},
{"movie_genre":"Comedy|Fantasy|Horror|Musical|Thriller","movie_title":"Phantom of the Paradise"},
{"movie_genre":"Horror|Sci-Fi","movie_title":"Empire of the Ants"},
{"movie_genre":"Drama|Romance|War","movie_title":"Becky Sharp"},
{"movie_genre":"Action|Drama|Thriller","movie_title":"Where a Good Man Goes (Joi gin a long)"},
{"movie_genre":"Adventure|Children|Drama","movie_title":"Barnens ö"},
{"movie_genre":"Action|Crime|Thriller","movie_title":"Ninja: Shadow of a Tear"},
{"movie_genre":"Drama","movie_title":"Violette"},
{"movie_genre":"Drama|Romance","movie_title":"Lonely Passion of Judith Hearne, The"},
{"movie_genre":"Drama|Film-Noir","movie_title":"Mildred Pierce"},
{"movie_genre":"Comedy|Romance","movie_title":"It's Complicated"},
{"movie_genre":"Drama","movie_title":"Squeeze"},
{"movie_genre":"Comedy","movie_title":"Faithful"},
{"movie_genre":"Comedy|Drama","movie_title":"Hana (Hana yori mo naho)"},
{"movie_genre":"Comedy","movie_title":"Mistress"},
{"movie_genre":"Comedy|Musical","movie_title":"Volga - Volga"},
{"movie_genre":"Drama","movie_title":"Little Foxes, The"},
{"movie_genre":"Action|Adventure|Sci-Fi","movie_title":"Flash Gordon"},
{"movie_genre":"Horror|Sci-Fi|Thriller","movie_title":"Endangered Species"},
{"movie_genre":"Western","movie_title":"Last Sunset, The"},
{"movie_genre":"Comedy","movie_title":"Honeymoons"},
{"movie_genre":"Drama","movie_title":"Rudy"},
{"movie_genre":"Drama|Romance","movie_title":"Mumblecore"},
{"movie_genre":"Action","movie_title":"Shaolin Temple, The (Shao Lin Si)"},
{"movie_genre":"Sci-Fi|Thriller","movie_title":"State of Emergency"},
{"movie_genre":"Action|Drama","movie_title":"Target"},
{"movie_genre":"Drama|Romance","movie_title":"Like Sunday, Like Rain"},
{"movie_genre":"Action","movie_title":"American Ninja 4: The Annihilation"},
{"movie_genre":"Drama|War","movie_title":"Andrei Rublev (Andrey Rublyov)"},
{"movie_genre":"Crime|Horror|Mystery|Thriller","movie_title":"Book of Shadows: Blair Witch 2"},
{"movie_genre":"Horror","movie_title":"Dark Circles "},
{"movie_genre":"Documentary","movie_title":"Questioning Darwin"},
{"movie_genre":"Drama","movie_title":"Not Without My Daughter"},
{"movie_genre":"Drama|Romance","movie_title":"Honey"},
{"movie_genre":"Documentary","movie_title":"Ingmar Bergman on Life and Work (Ingmar Bergman: Om liv och arbete)"},
{"movie_genre":"Documentary","movie_title":"American Nightmare, The"},
{"movie_genre":"Drama|Romance","movie_title":"Our Daily Bread"},
{"movie_genre":"Drama","movie_title":"Naked Kiss, The"},
{"movie_genre":"Documentary","movie_title":"Parking Lot Movie, The"},
{"movie_genre":"Comedy|Documentary","movie_title":"DysFunktional Family"},
{"movie_genre":"Comedy|Drama","movie_title":"Bombón: El Perro (El perro)"},
{"movie_genre":"Action|Comedy|Horror|Romance|Sci-Fi","movie_title":"Wild Zero"},
{"movie_genre":"Crime","movie_title":"The Police Can't Move"},
{"movie_genre":"Drama|War","movie_title":"Admiral"},
{"movie_genre":"Horror","movie_title":"House of Dracula"},
{"movie_genre":"Drama","movie_title":"Hands Over the City (Le mani sulla città)"},
{"movie_genre":"Drama","movie_title":"The Woodcarver"},
{"movie_genre":"Action|Animation|Children|Fantasy","movie_title":"Looney Tunes: Back in Action"},
{"movie_genre":"Horror","movie_title":"Subspecies IV: Bloodstorm"},
{"movie_genre":"Comedy|Drama|Romance","movie_title":"Romantics, The"},
{"movie_genre":"Adventure|Horror|Romance|Sci-Fi","movie_title":"Island of Lost Souls"},
{"movie_genre":"Drama|Romance","movie_title":"Pear Tree, The (Derakhte Golabi)"},
{"movie_genre":"Drama","movie_title":"Palo Alto"},
{"movie_genre":"Action|Comedy","movie_title":"Brain Smasher... A Love Story (Bouncer and the Lady, The)"},
{"movie_genre":"Comedy|Romance","movie_title":"Serendipity"},
{"movie_genre":"Horror","movie_title":"American Horror House (Sorority Horror House)"},
{"movie_genre":"Drama","movie_title":"Lake, A (Un lac)"},
{"movie_genre":"Horror|Sci-Fi","movie_title":"Teenagers from Outer Space"},
{"movie_genre":"Action|Comedy|Sci-Fi","movie_title":"Tank Girl"},
{"movie_genre":"Comedy|Drama","movie_title":"Chiedimi se sono felice"},
{"movie_genre":"Drama","movie_title":"Jo Pour Jonathan"},
{"movie_genre":"Comedy","movie_title":"Without a Paddle"},
{"movie_genre":"Action|Thriller","movie_title":"Blind Fury"},
{"movie_genre":"Drama|Mystery|Thriller","movie_title":"Village, The"},
{"movie_genre":"Documentary","movie_title":"Mi Amigo Hugo"},
{"movie_genre":"Drama","movie_title":"Higher Learning"},
{"movie_genre":"Comedy|War","movie_title":"Russians Are Coming, the Russians Are Coming, The"},
{"movie_genre":"Crime|Drama|Film-Noir|Romance","movie_title":"Johnny Apollo"},
{"movie_genre":"Comedy|Romance","movie_title":"Strange Planet"},
{"movie_genre":"Drama|War","movie_title":"Peck on the Cheek, A (Kannathil Muthamittal)"},
{"movie_genre":"Drama","movie_title":"Desert Flower"},
{"movie_genre":"Comedy|Romance","movie_title":"Foreign Affair, A"},
{"movie_genre":"Crime|Drama|Film-Noir","movie_title":"Phenix City Story, The"},
{"movie_genre":"Drama|Film-Noir|Thriller","movie_title":"Thieves' Highway"},
{"movie_genre":"Comedy","movie_title":"National Lampoon's Cattle Call (Cattle Call)"},
{"movie_genre":"Drama|Film-Noir|Romance","movie_title":"Set-Up, The"},
{"movie_genre":"Drama|Musical|Romance|War","movie_title":"North Star, The"},
{"movie_genre":"Horror|Thriller","movie_title":"Relic, The"},
{"movie_genre":"Documentary|Drama","movie_title":"Tigrero: A Film That Was Never Made"},
{"movie_genre":"Drama|Thriller","movie_title":"Dischord"},
{"movie_genre":"Drama|Musical","movie_title":"Oxygen"},
{"movie_genre":"Comedy|Drama|Romance","movie_title":"Mad Dog and Glory"},
{"movie_genre":"Children|Comedy","movie_title":"Heavyweights (Heavy Weights)"},
{"movie_genre":"Crime|Drama|Horror","movie_title":"Chaos"},
{"movie_genre":"Adventure|Comedy","movie_title":"Abbott and Costello in the Foreign Legion"},
{"movie_genre":"Drama","movie_title":"Stopped on Track"},
{"movie_genre":"Crime|Drama|Mystery|Thriller","movie_title":"Pledge, The"},
{"movie_genre":"Drama","movie_title":"Timbuktu"},
{"movie_genre":"Drama","movie_title":"Forest of the Gods (Dievu miskas)"},
{"movie_genre":"Comedy","movie_title":"Boat Trip"},
{"movie_genre":"Comedy","movie_title":"Meatballs III"},
{"movie_genre":"Drama|Film-Noir|Thriller","movie_title":"Bribe, The"},
{"movie_genre":"Action|Horror","movie_title":"Screamers"},
{"movie_genre":"Drama","movie_title":"Virgin Stripped Bare by Her Bachelors (Oh! Soo-jung)"},
{"movie_genre":"Drama|Romance","movie_title":"Unfinished Sky"},
{"movie_genre":"Action|Comedy|Sci-Fi","movie_title":"Hell Comes to Frogtown"},
{"movie_genre":"Comedy|Romance","movie_title":"Management"},
{"movie_genre":"Documentary","movie_title":"Life Apart: Hasidism in America, A"},
{"movie_genre":"Animation","movie_title":"Trick or Treat"},
{"movie_genre":"Comedy|Mystery","movie_title":"By the Pricking of My Thumbs (Mon petit doigt m'a dit...)"},
{"movie_genre":"Documentary","movie_title":"Mystery of Picasso, The (Le mystère Picasso)"},
{"movie_genre":"Action|Adventure","movie_title":"Big Game"},
{"movie_genre":"Musical|Romance","movie_title":"Easter Parade"},
{"movie_genre":"Comedy","movie_title":"All Over the Guy"},
{"movie_genre":"Documentary","movie_title":"Al Franken: God Spoke"},
{"movie_genre":"Action|Adventure|Children|Comedy","movie_title":"Agent Cody Banks 2: Destination London"},
{"movie_genre":"Action|Crime","movie_title":"Taking of Pelham One Two Three, The"},
{"movie_genre":"Comedy","movie_title":"One Crazy Summer"},
{"movie_genre":"Documentary","movie_title":"Mansome"},
{"movie_genre":"Comedy|Drama","movie_title":"Reluctant Debutante, The"},
{"movie_genre":"Action","movie_title":"13 Assassins (Jûsan-nin no shikaku)"},
{"movie_genre":"Action|Comedy","movie_title":"Half a Loaf of Kung Fu (Dian zhi gong fu gan chian chan)"},
{"movie_genre":"Sci-Fi","movie_title":"Mission to Mars"},
{"movie_genre":"Drama","movie_title":"Goya's Ghosts"},
{"movie_genre":"Documentary","movie_title":"Message to Love: The Isle of Wight Festival"},
{"movie_genre":"Comedy","movie_title":"Tommy Boy"},
{"movie_genre":"Drama|War","movie_title":"Diplomacy (Diplomatie)"},
{"movie_genre":"Crime|Drama|Mystery|Thriller","movie_title":"Betrayed, The"},
{"movie_genre":"Drama","movie_title":"Marion Bridge"},
{"movie_genre":"Drama|Romance","movie_title":"Such Is Life (Así es la vida...)"},
{"movie_genre":"Drama","movie_title":"Nixon"},
{"movie_genre":"Drama","movie_title":"Estomago: A Gastronomic Story"},
{"movie_genre":"Comedy","movie_title":"Orgazmo"},
{"movie_genre":"Horror","movie_title":"Dark Circles "},
{"movie_genre":"Comedy","movie_title":"Bikini Summer II"},
{"movie_genre":"Documentary","movie_title":"11th Hour, The"},
{"movie_genre":"Drama","movie_title":"Cincinnati Kid, The"},
{"movie_genre":"Comedy","movie_title":"Napoleon Dynamite"},
{"movie_genre":"Animation","movie_title":"The Periwig-Maker"},
{"movie_genre":"Drama|Thriller","movie_title":"Snakes and Earrings (Hebi ni piasu)"},
{"movie_genre":"Comedy","movie_title":"Girl from Jones Beach, The"},
{"movie_genre":"Documentary","movie_title":"Chesty: A Tribute to a Legend"},
{"movie_genre":"Crime|Documentary","movie_title":"Prison Terminal: The Last Days of Private Jack Hall"},
{"movie_genre":"Drama","movie_title":"Henry IV, Part II (Second Part of King Henry the Fourth, including his death and the coronation of King Henry the Fifth, The)"},
{"movie_genre":"Drama","movie_title":"Guilty (Présumé coupable)"},
{"movie_genre":"Drama","movie_title":"I Dreamed of Africa"},
{"movie_genre":"Drama","movie_title":"Blind Chance (Przypadek)"},
{"movie_genre":"Drama|Romance","movie_title":"Dog Tags"},
{"movie_genre":"Drama","movie_title":"Danton"},
{"movie_genre":"Comedy|Drama|Romance","movie_title":"Just Buried"},
{"movie_genre":"Action|Adventure|Drama|War","movie_title":"King Arthur"},
{"movie_genre":"Comedy","movie_title":"Death in Brunswick"},
{"movie_genre":"Romance|War","movie_title":"Farewell to Arms, A"},
{"movie_genre":"Comedy","movie_title":"Plácido"},
{"movie_genre":"Comedy|Drama","movie_title":"Visions of Europe"},
{"movie_genre":"Drama","movie_title":"Bee Season"},
{"movie_genre":"Drama","movie_title":"Mother, I Love You"},
{"movie_genre":"Comedy","movie_title":"Me and Him (Ich und Er)"},
{"movie_genre":"Drama","movie_title":"All Over Me"},
{"movie_genre":"Crime|Mystery|Thriller","movie_title":"Now You See Me"},
{"movie_genre":"Crime|Thriller","movie_title":"Mother Knows Best"},
{"movie_genre":"Crime|Drama","movie_title":"Stormy Monday"},
{"movie_genre":"Comedy|Drama","movie_title":"Buddy"},
{"movie_genre":"Action|Comedy|Drama","movie_title":"Below the Belt"},
{"movie_genre":"Adventure|Animation","movie_title":"Frozen Fever"},
{"movie_genre":"Documentary","movie_title":"Leave The World Behind"},
{"movie_genre":"Documentary","movie_title":"Metsän tarina"},
{"movie_genre":"Drama|Horror","movie_title":"Possession"},
{"movie_genre":"Drama","movie_title":"Four Friends (a.k.a. Georgia's Friends)"},
{"movie_genre":"Horror","movie_title":"Bag of Bones"},
{"movie_genre":"Crime|Drama|Film-Noir","movie_title":"Hollow Triumph (a.k.a. The Scar)"},
{"movie_genre":"Comedy|Drama|Romance","movie_title":"Purple Violets"},
{"movie_genre":"Action|Adventure|Sci-Fi|Thriller|War","movie_title":"Captain America: The First Avenger"},
{"movie_genre":"Drama","movie_title":"Social Network, The"},
{"movie_genre":"Drama|Romance","movie_title":"Angels and Insects"},
{"movie_genre":"Documentary|Musical","movie_title":"Stevie Nicks: Live at Red Rocks"},
{"movie_genre":"Documentary","movie_title":"Pulling John"},
{"movie_genre":"Documentary","movie_title":"Altman"},
{"movie_genre":"War","movie_title":"Operation Daybreak"},
{"movie_genre":"Drama","movie_title":"Deuces Wild"},
{"movie_genre":"Drama","movie_title":"Thousand Acres, A"},
{"movie_genre":"Drama","movie_title":"Todos eran culpables"},
{"movie_genre":"Action|Mystery|Thriller","movie_title":"Power 98"},
{"movie_genre":"Action|Adventure|Crime|IMAX","movie_title":"Dark Knight Rises, The"},
{"movie_genre":"Documentary|War","movie_title":"Sorrow and the Pity, The (Le chagrin et la pitié)"},
{"movie_genre":"Action|Crime|Thriller","movie_title":"Telefon"},
{"movie_genre":"Crime|Drama|Romance","movie_title":"Internes Can't Take Money"},
{"movie_genre":"Drama","movie_title":"Designated Mourner, The"},
{"movie_genre":"Action|Crime|Thriller","movie_title":"Ticker"},
{"movie_genre":"Drama","movie_title":"Of Love and Shadows"},
{"movie_genre":"Drama","movie_title":"Get Over It"},
{"movie_genre":"Comedy","movie_title":"You're Missing the Point"},
{"movie_genre":"War","movie_title":"Battle of Britain"},
{"movie_genre":"Adventure|Children","movie_title":"Legend of Lobo, The"},
{"movie_genre":"Action|Comedy","movie_title":"Grand Theft Auto"},
{"movie_genre":"(no genres listed)","movie_title":"Love Steaks"},
{"movie_genre":"Romance","movie_title":"Sexual Life"},
{"movie_genre":"Adventure|Sci-Fi","movie_title":"At the Earth's Core"},
{"movie_genre":"Drama","movie_title":"Vision (Vision - Aus dem Leben der Hildegard von Bingen)"},
{"movie_genre":"Comedy","movie_title":"People, Places, Things"},
{"movie_genre":"Horror|Sci-Fi","movie_title":"Parasite"},
{"movie_genre":"Crime|Drama","movie_title":"Carlito's Way"},
{"movie_genre":"Drama|War","movie_title":"War Horse"},
{"movie_genre":"Documentary","movie_title":"Startup.com"},
{"movie_genre":"Documentary|Musical","movie_title":"Sign 'o' the Times"},
{"movie_genre":"Horror|Thriller","movie_title":"House of Wax"},
{"movie_genre":"Drama|Thriller","movie_title":"The Stanford Prison Experiment"},
{"movie_genre":"Drama","movie_title":"Crazy as Hell"},
{"movie_genre":"Animation|Children|Fantasy|War","movie_title":"Small Soldiers"},
{"movie_genre":"Horror|Mystery","movie_title":"Bloody New Year"},
{"movie_genre":"Romance|Thriller","movie_title":"Attack, The"},
{"movie_genre":"Drama|Horror|Thriller","movie_title":"Dumplings (Gaau ji)"},
{"movie_genre":"Comedy|Romance|Thriller|Western","movie_title":"Rainmaker, The"},
{"movie_genre":"Action|Animation|Comedy|Crime|Drama|Mystery|Romance|Thriller","movie_title":"Lupin III: First Contact (Rupan Sansei: Faasuto Kontakuto)"},
{"movie_genre":"Comedy|Horror","movie_title":"Ghoulies II"},
{"movie_genre":"Documentary","movie_title":"Bush's Brain"},
{"movie_genre":"Crime|Mystery|Thriller","movie_title":"Righteous Kill"},
{"movie_genre":"Action|Drama|War","movie_title":"Bullet in the Head"},
{"movie_genre":"Mystery|Thriller","movie_title":"Midnight Lace"},
{"movie_genre":"Comedy|Crime","movie_title":"King's Ransom"},
{"movie_genre":"Drama","movie_title":"I Belong (Som du ser meg)"},
{"movie_genre":"Documentary","movie_title":"Serving Life"},
{"movie_genre":"Adventure|Comedy|Sci-Fi","movie_title":"Our Man Flint"},
{"movie_genre":"Drama","movie_title":"Sunshine"},
{"movie_genre":"Documentary","movie_title":"American Movie"},
{"movie_genre":"Action|Sci-Fi|Thriller","movie_title":"Alien Hunter"},
{"movie_genre":"Action|Adventure|Crime|Thriller","movie_title":"Hobo with a Shotgun"},
{"movie_genre":"Drama","movie_title":"O"},
{"movie_genre":"Drama|Thriller","movie_title":"Two-Minute Warning"},
{"movie_genre":"Comedy","movie_title":"Waiting for Guffman"},
{"movie_genre":"Fantasy","movie_title":"Dreams That Money Can Buy"},
{"movie_genre":"Action|Horror|Sci-Fi|War|Western","movie_title":"Book of Fate, The (Kohtalon kirja)"},
{"movie_genre":"Comedy","movie_title":"Holiday (Jour de fête)"},
{"movie_genre":"Comedy","movie_title":"I'm No Angel"},
{"movie_genre":"Action|Crime","movie_title":"Showdown in Little Tokyo"},
{"movie_genre":"Crime|Drama","movie_title":"Child, The (L'enfant)"},
{"movie_genre":"Comedy|Romance","movie_title":"Playing It Cool"},
{"movie_genre":"Documentary|Musical","movie_title":"Pearl Jam: Immagine in Cornice - Live in Italy 2006"},
{"movie_genre":"Comedy|Drama","movie_title":"Greenfingers"},
{"movie_genre":"Action|Comedy|Horror|Thriller","movie_title":"Feast"},
{"movie_genre":"Drama","movie_title":"Sunlight Jr."}]